monkey_utils/__init__.py
monkey_utils/configure.py
monkey_utils/helpers.py
monkey_utils/resource.py
monkey_utils-1.0.3.dist-info/LICENSE.txt
monkey_utils-1.0.3.dist-info/METADATA
monkey_utils-1.0.3.dist-info/WHEEL
monkey_utils-1.0.3.dist-info/RECORD
